[
  {
    "title": "SXSW 2018 - Top Trends",
    "pptId": "95762681",
    "imageurl": "//cdn.slidesharecdn.com/ss_thumbnails/sxsw2018-180502232324-thumbnail-3.jpg?cb=1525303577",
    "ajax": "false",
    "gaCat": "list_page_loggedin",
    "gaAction": "slideshow_thumbnail",
    "gaLabel": "img_link_click",
    "link": "https://www.slideshare.net/ZazzaNM/sxsw-2018-top-trends"
  },
  {
    "title": "Scalaz 8: A Whole New Game",
    "pptId": "95821660",
    "imageurl": "//cdn.slidesharecdn.com/ss_thumbnails/scalaz8awholenewgame-flatmaposlo2018-180503124057-thumbnail-3.jpg?cb=1525351437",
    "ajax": "false",
    "gaCat": "list_page_loggedin",
    "gaAction": "slideshow_thumbnail",
    "gaLabel": "img_link_click",
    "link": "https://www.slideshare.net/jdegoes/scalaz-8-a-whole-new-game"
  },
  {
    "title": "Mothers Day gifts to Davanagere, Mothers Day Flowers delivery in Davanagere",
    "pptId": "95807322",
    "imageurl": "//cdn.slidesharecdn.com/ss_thumbnails/mothers-day-gifts-to-davanagere-180503091356-thumbnail-3.jpg?cb=1525338966",
    "ajax": "false",
    "gaCat": "list_page_loggedin",
    "gaAction": "slideshow_thumbnail",
    "gaLabel": "img_link_click",
    "link": "https://www.slideshare.net/akshatashetty8/mothers-day-gifts-to-davanagere-mothers-day-flowers-delivery-in-davanagere"
  },
  {
    "title": "Financial Statement Analysis and Financial Models",
    "pptId": "95807427",
    "imageurl": "//cdn.slidesharecdn.com/ss_thumbnails/financialstatementanalysisandfinancialmodels-180503091510-thumbnail-3.jpg?cb=1525339047",
    "ajax": "false",
    "gaCat": "list_page_loggedin",
    "gaAction": "slideshow_thumbnail",
    "gaLabel": "img_link_click",
    "link": "https://www.slideshare.net/KananEXIMMaksudulHuq/financial-statement-analysis-and-financial-models"
  },
  {
    "title": "複合趨向補語練習",
    "pptId": "95764561",
    "imageurl": "//cdn.slidesharecdn.com/ss_thumbnails/quiangcomplentes-180502235659-thumbnail-3.jpg?cb=1525305458",
    "ajax": "false",
    "gaCat": "list_page_loggedin",
    "gaAction": "slideshow_thumbnail",
    "gaLabel": "img_link_click",
    "link": "https://www.slideshare.net/HettyHsiao/ss-95764561"
  },
  {
    "title": "Turismo espacial",
    "pptId": "95860981",
    "imageurl": "//cdn.slidesharecdn.com/ss_thumbnails/turismoespacial-180503183704-thumbnail-3.jpg?cb=1525372836",
    "ajax": "false",
    "gaCat": "list_page_loggedin",
    "gaAction": "slideshow_thumbnail",
    "gaLabel": "img_link_click",
    "link": "https://www.slideshare.net/mariaortizcorredor/turismo-espacial-95860981"
  },
  {
    "title": "La vida en Marte ",
    "pptId": "95862091",
    "imageurl": "//cdn.slidesharecdn.com/ss_thumbnails/lavidaenmarte5-180503184632-thumbnail-3.jpg?cb=1525373295",
    "ajax": "false",
    "gaCat": "list_page_loggedin",
    "gaAction": "slideshow_thumbnail",
    "gaLabel": "img_link_click",
    "link": "https://www.slideshare.net/NataRico/la-vida-en-marte"
  },
  {
    "title": "Ops Happens:  Improving Incident Response Using DevOps and SRE Practices",
    "pptId": "95854226",
    "imageurl": "//cdn.slidesharecdn.com/ss_thumbnails/damonedwards-interoplasvegas2018-opshappens-180503173511-thumbnail-3.jpg?cb=1525369189",
    "ajax": "false",
    "gaCat": "list_page_loggedin",
    "gaAction": "slideshow_thumbnail",
    "gaLabel": "img_link_click",
    "link": "https://www.slideshare.net/Rundeck/ops-happens-improving-incident-response-using-devops-and-sre-practices"
  },
  {
    "title": "New trends to look out for 2018 winter season",
    "pptId": "95812374",
    "imageurl": "//cdn.slidesharecdn.com/ss_thumbnails/new-trends-to-look-out-for-2018-winter-season-180503101550-thumbnail-3.jpg?cb=1525342670",
    "ajax": "false",
    "gaCat": "list_page_loggedin",
    "gaAction": "slideshow_thumbnail",
    "gaLabel": "img_link_click",
    "link": "https://www.slideshare.net/femmeconnections/new-trends-to-look-out-for-2018-winter-season"
  },
  {
    "title": "5 Active Medical Marijuana Components",
    "pptId": "95816462",
    "imageurl": "//cdn.slidesharecdn.com/ss_thumbnails/5activemarijuanacomponents-180503111903-thumbnail-3.jpg?cb=1525346392",
    "ajax": "false",
    "gaCat": "list_page_loggedin",
    "gaAction": "slideshow_thumbnail",
    "gaLabel": "img_link_click",
    "link": "https://www.slideshare.net/onlinemedicalcard/5-active-medical-marijuana-components"
  },
  {
    "title": "Turismo espacial 3",
    "pptId": "95860973",
    "imageurl": "//cdn.slidesharecdn.com/ss_thumbnails/turismoespacial3-180503183659-thumbnail-3.jpg?cb=1525372867",
    "ajax": "false",
    "gaCat": "list_page_loggedin",
    "gaAction": "slideshow_thumbnail",
    "gaLabel": "img_link_click",
    "link": "https://www.slideshare.net/karendanielapinedaal/turismo-espacial-3"
  },
  {
    "title": "IoT Edge Processing with Apache NiFi and MiniFi and Apache MXNet for IoT NY 2018",
    "pptId": "95838550",
    "imageurl": "//cdn.slidesharecdn.com/ss_thumbnails/iotapachenifiminifimxnet-180503152424-thumbnail-3.jpg?cb=1525361233",
    "ajax": "false",
    "gaCat": "list_page_loggedin",
    "gaAction": "slideshow_thumbnail",
    "gaLabel": "img_link_click",
    "link": "https://www.slideshare.net/bunkertor/iot-edge-processing-with-apache-nifi-and-minifi-and-apache-mxnet-for-iot-ny-2018"
  },
  {
    "title": "Uv spectroscopy",
    "pptId": "95798625",
    "imageurl": "//cdn.slidesharecdn.com/ss_thumbnails/uvspectroscopy-180503073757-thumbnail-3.jpg?cb=1525333322",
    "ajax": "false",
    "gaCat": "list_page_loggedin",
    "gaAction": "slideshow_thumbnail",
    "gaLabel": "img_link_click",
    "link": "https://www.slideshare.net/422459/uv-spectroscopy-95798625"
  },
  {
    "title": "20180503 kube con eu   kubernetes metrics deep dive",
    "pptId": "95822729",
    "imageurl": "//cdn.slidesharecdn.com/ss_thumbnails/20180503kubeconeu-kubernetesmetricsdeepdive-180503125632-thumbnail-3.jpg?cb=1525352322",
    "ajax": "false",
    "gaCat": "list_page_loggedin",
    "gaAction": "slideshow_thumbnail",
    "gaLabel": "img_link_click",
    "link": "https://www.slideshare.net/BobCotton2/20180503-kube-con-eu-kubernetes-metrics-deep-dive"
  },
  {
    "title": "Golden triangle tour package to himachal   shimla manali honeymoon",
    "pptId": "95798364",
    "imageurl": "//cdn.slidesharecdn.com/ss_thumbnails/goldentriangletourpackagetohimachal-shimlamanalihoneymoon-180503073524-thumbnail-3.jpg?cb=1525333123",
    "ajax": "false",
    "gaCat": "list_page_loggedin",
    "gaAction": "slideshow_thumbnail",
    "gaLabel": "img_link_click",
    "link": "https://www.slideshare.net/trip9999/golden-triangle-tour-package-to-himachal-shimla-manali-honeymoon"
  },
  {
    "title": "Exterior Dress Up Products  for Scion FR-S and Subaru BR-Z at SubieDepot",
    "pptId": "95794072",
    "imageurl": "//cdn.slidesharecdn.com/ss_thumbnails/exteriordressupproductsforscionfr-sandsubarubr-zatsubiedepot-180503064908-thumbnail-3.jpg?cb=1525330182",
    "ajax": "false",
    "gaCat": "list_page_loggedin",
    "gaAction": "slideshow_thumbnail",
    "gaLabel": "img_link_click",
    "link": "https://www.slideshare.net/SubieDepotCA/exterior-dress-up-products-for-scion-frs-and-subaru-brz-at-subiedepot"
  },
  {
    "title": "Pendidikan Agama Islam - Islam, Perempuan dan Feminisme ",
    "pptId": "95838176",
    "imageurl": "//cdn.slidesharecdn.com/ss_thumbnails/pai-180503152140-thumbnail-3.jpg?cb=1525360965",
    "ajax": "false",
    "gaCat": "list_page_loggedin",
    "gaAction": "slideshow_thumbnail",
    "gaLabel": "img_link_click",
    "link": "https://www.slideshare.net/Farichaalif17/pendidikan-agama-islam-islam-perempuan-dan-feminisme"
  },
  {
    "title": "Эра блокчейна: как это будет",
    "pptId": "95788378",
    "imageurl": "//cdn.slidesharecdn.com/ss_thumbnails/genkin-180503054335-thumbnail-3.jpg?cb=1525326568",
    "ajax": "false",
    "gaCat": "list_page",
    "gaAction": "slideshow_thumbnail",
    "gaLabel": "img_link_click",
    "link": "https://www.slideshare.net/nanbelarus/ss-95788378"
  },
  {
    "title": "Chest pain in children",
    "pptId": "95761201",
    "imageurl": "//cdn.slidesharecdn.com/ss_thumbnails/chestpaininchildren-180502225808-thumbnail-3.jpg?cb=1525301917",
    "ajax": "false",
    "gaCat": "list_page",
    "gaAction": "slideshow_thumbnail",
    "gaLabel": "img_link_click",
    "link": "https://www.slideshare.net/azadhaleem/chest-pain-in-children"
  },
  {
    "title": "Ho feng shan",
    "pptId": "95807488",
    "imageurl": "//cdn.slidesharecdn.com/ss_thumbnails/hofengshan-180503091546-thumbnail-3.jpg?cb=1525341283",
    "ajax": "false",
    "gaCat": "list_page",
    "gaAction": "slideshow_thumbnail",
    "gaLabel": "img_link_click",
    "link": "https://www.slideshare.net/liceolevi/ho-feng-shan-95807488"
  },
  {
    "title": "20180503行政院科技會報辦公室：「數位國家‧創新經濟發展方案(2017~2025年)推動成果」報告（簡報）",
    "pptId": "95768786",
    "imageurl": "//cdn.slidesharecdn.com/ss_thumbnails/1-1bostan-180503012226-thumbnail-3.jpg?cb=1525315780",
    "ajax": "false",
    "gaCat": "list_page",
    "gaAction": "slideshow_thumbnail",
    "gaLabel": "img_link_click",
    "link": "https://www.slideshare.net/OpenMic1/2018050320172025-95768786"
  },
  {
    "title": "Securing Voting Infrastructure before the Mid-Term Elections",
    "pptId": "95749435",
    "imageurl": "//cdn.slidesharecdn.com/ss_thumbnails/securingvotinginfrastructurebeforethemid-termelections-180502200435-thumbnail-3.jpg?cb=1525292012",
    "ajax": "false",
    "gaCat": "list_page",
    "gaAction": "slideshow_thumbnail",
    "gaLabel": "img_link_click",
    "link": "https://www.slideshare.net/denimgroup/securing-voting-infrastructure-before-the-midterm-elections"
  },
  {
    "title": "Принципиальные переговоры",
    "pptId": "95797828",
    "imageurl": "//cdn.slidesharecdn.com/ss_thumbnails/principlednegotiation-180503072957-thumbnail-3.jpg?cb=1525332730",
    "ajax": "false",
    "gaCat": "list_page",
    "gaAction": "slideshow_thumbnail",
    "gaLabel": "img_link_click",
    "link": "https://www.slideshare.net/AndreyHaletsky/ss-95797828"
  },
  {
    "title": "Sosyal Mühendislik - BAU Cyber Talks 02/05/2018",
    "pptId": "95758793",
    "imageurl": "//cdn.slidesharecdn.com/ss_thumbnails/bau-180502221716-thumbnail-3.jpg?cb=1525299613",
    "ajax": "false",
    "gaCat": "list_page",
    "gaAction": "slideshow_thumbnail",
    "gaLabel": "img_link_click",
    "link": "https://www.slideshare.net/RaifBerkayDNEL/sosyal-mhendislik-bau-cyber-talks-02052018"
  },
  {
    "title": "Power Systems Training Course for Non-Engineers",
    "pptId": "95846391",
    "imageurl": "//cdn.slidesharecdn.com/ss_thumbnails/powersystemsfornon-engineers-180503162621-thumbnail-3.jpg?cb=1525365209",
    "ajax": "false",
    "gaCat": "list_page",
    "gaAction": "slideshow_thumbnail",
    "gaLabel": "img_link_click",
    "link": "https://www.slideshare.net/tonextraining/power-systems-training-course-for-nonengineers"
  },
  {
    "title": "Canvas & Credly Webinar - 5/2/18",
    "pptId": "95826670",
    "imageurl": "//cdn.slidesharecdn.com/ss_thumbnails/canvaspartnerwebcast-credlyfinalv2-180503134534-thumbnail-3.jpg?cb=1525355160",
    "ajax": "false",
    "gaCat": "list_page",
    "gaAction": "slideshow_thumbnail",
    "gaLabel": "img_link_click",
    "link": "https://www.slideshare.net/PatriciaDiaz80/canvas-credly-webinar-5218"
  },
  {
    "title": "Dash Lock & Key Locksmith Services",
    "pptId": "95791742",
    "imageurl": "//cdn.slidesharecdn.com/ss_thumbnails/dashlocknkey-180503062129-thumbnail-3.jpg?cb=1525328575",
    "ajax": "false",
    "gaCat": "list_page",
    "gaAction": "slideshow_thumbnail",
    "gaLabel": "img_link_click",
    "link": "https://www.slideshare.net/dashlocknkey/dash-lock-key-locksmith-services"
  },
  {
    "title": "Buy Books    Health Care USA: Understanding Its Organization and Delivery  by Harry A. Sultz   Free ",
    "pptId": "95780680",
    "imageurl": "//cdn.slidesharecdn.com/ss_thumbnails/buybookshealthcareusa-180503041504-thumbnail-3.jpg?cb=1525320923",
    "ajax": "false",
    "gaCat": "list_page",
    "gaAction": "slideshow_thumbnail",
    "gaLabel": "img_link_click",
    "link": "https://www.slideshare.net/haxahememo/buy-books-health-care-usa-understanding-its-organization-and-delivery-by-harry-a-sultz-free"
  },
  {
    "title": "Lectura fácil. Charla informativa Programa ACEX",
    "pptId": "95749304",
    "imageurl": "//cdn.slidesharecdn.com/ss_thumbnails/20180425-charlaie-acex-180502200313-thumbnail-3.jpg?cb=1525291519",
    "ajax": "false",
    "gaCat": "list_page",
    "gaAction": "slideshow_thumbnail",
    "gaLabel": "img_link_click",
    "link": "https://www.slideshare.net/colectivoacex/lectura-fcil-charla-informativa-programa-acex"
  },
  {
    "title": "Science seminar 2016",
    "pptId": "95821732",
    "imageurl": "//cdn.slidesharecdn.com/ss_thumbnails/scienceseminar2016-180503124202-thumbnail-3.jpg?cb=1525351457",
    "ajax": "false",
    "gaCat": "list_page",
    "gaAction": "slideshow_thumbnail",
    "gaLabel": "img_link_click",
    "link": "https://www.slideshare.net/BirendraAcharya1/science-seminar-2016"
  },
  {
    "title": "Η ΧΛΩΡΙΔΑ ΚΑΙ Η ΠΑΝΙΔΑ ΣΤΟ ΝΗΣΙ ΤΗΣ ΡΟΔΟΥ",
    "pptId": "95806044",
    "imageurl": "//cdn.slidesharecdn.com/ss_thumbnails/xloridakaipanidaok-180503085948-thumbnail-3.jpg?cb=1525339428",
    "ajax": "false",
    "gaCat": "list_page",
    "gaAction": "slideshow_thumbnail",
    "gaLabel": "img_link_click",
    "link": "https://www.slideshare.net/tinamantikou/ss-95806044"
  },
  {
    "title": "Golden triangle tour package to himachal   shimla manali honeymoon",
    "pptId": "95798364",
    "imageurl": "//cdn.slidesharecdn.com/ss_thumbnails/goldentriangletourpackagetohimachal-shimlamanalihoneymoon-180503073524-thumbnail-3.jpg?cb=1525333123",
    "ajax": "false",
    "gaCat": "list_page",
    "gaAction": "slideshow_thumbnail",
    "gaLabel": "img_link_click",
    "link": "https://www.slideshare.net/trip9999/golden-triangle-tour-package-to-himachal-shimla-manali-honeymoon"
  },
  {
    "title": " Read English Made Easy Volume One: A New ESL Approach: Learning English Through Pictures: 1  by Jonathan Crichton   Unlimited ",
    "pptId": "95804194",
    "imageurl": "//cdn.slidesharecdn.com/ss_thumbnails/readenglishmadeeasy-180503083916-thumbnail-3.jpg?cb=1525336786",
    "ajax": "false",
    "gaCat": "list_page",
    "gaAction": "slideshow_thumbnail",
    "gaLabel": "img_link_click",
    "link": "https://www.slideshare.net/sixuda/read-english-made-easy-volume-one-a-new-esl-approach-learning-english-through-pictures-1-by-jonathan-crichton-unlimited"
  },
  {
    "title": "Pharmaceutical Contaminants in water recovery facilities",
    "pptId": "95787415",
    "imageurl": "//cdn.slidesharecdn.com/ss_thumbnails/teamtamcfinalpharmaceuticalwastewater1-180503053320-thumbnail-3.jpg?cb=1525326390",
    "ajax": "false",
    "gaCat": "list_page",
    "gaAction": "slideshow_thumbnail",
    "gaLabel": "img_link_click",
    "link": "https://www.slideshare.net/OLUWATOBILOBAAKINWAN/pharmaceutical-contaminanats-in-water-recovery-facilities"
  },
  {
    "title": "Progressive exposure using deployment rings and feature flags",
    "pptId": "95761182",
    "imageurl": "//cdn.slidesharecdn.com/ss_thumbnails/progressiveexposureusingdeploymentringsandfeatureflags-180502225751-thumbnail-3.jpg?cb=1529357812",
    "ajax": "false",
    "gaCat": "list_page",
    "gaAction": "slideshow_thumbnail",
    "gaLabel": "img_link_click",
    "link": "https://www.slideshare.net/WillyPeterSchaub/progressive-exposure-using-deployment-rings-and-feature-flags"
  }
]